prlps_typo/__init__.py
prlps_typo/typograf.js
prlps_typo-0.0.3.dist-info/LICENSE.txt
prlps_typo-0.0.3.dist-info/METADATA
prlps_typo-0.0.3.dist-info/WHEEL
prlps_typo-0.0.3.dist-info/top_level.txt
prlps_typo-0.0.3.dist-info/RECORD
