Metadata-Version: 2.1
Name: prlps_typo
Version: 0.0.3
Summary: исправление типографии в Markdown и HTML
Home-page: https://github.com/gniloyprolaps/prlps_typo
Author: prolapser
License: LICENSE.txt
Classifier: Development Status :: 4 - Beta
Classifier: Intended Audience :: Developers
Classifier: License :: OSI Approved :: MIT License
Classifier: Operating System :: OS Independent
Requires-Python: >=3.10
License-File: LICENSE.txt
Requires-Dist: py_mini_racer
Requires-Dist: html2text
Requires-Dist: mistune
Requires-Dist: httpx
